imageProcessing/__init__.py
imageProcessing/processing/__init__.py
imageProcessing/processing/combination.py
imageProcessing/processing/transformation.py
imageProcessing/utils/__init__.py
imageProcessing/utils/io.py
imageProcessing/utils/plot.py
imagemDIO-0.0.1.dist-info/METADATA
imagemDIO-0.0.1.dist-info/WHEEL
imagemDIO-0.0.1.dist-info/top_level.txt
imagemDIO-0.0.1.dist-info/RECORD
