Metadata-Version: 2.1
Name: imagemDIO
Version: 0.0.1
Summary: My short description
Home-page: 
Author: oliverborba
Author-email: lucas_borba@outlook.com
Requires-Python: >=3.8
